zoialib/__init__.py
zoialib/__main__.py
zoialib/file.py
zoialib/prepare.py
zoialib/rename.py
zoialib-0.6.0.dist-info/METADATA
zoialib-0.6.0.dist-info/WHEEL
zoialib-0.6.0.dist-info/entry_points.txt
zoialib-0.6.0.dist-info/RECORD
