Metadata-Version: 2.4
Name: zoialib
Version: 0.6.0
Summary: A patch librarian for the Empress ZOIA
Requires-Python: >=3.11
Requires-Dist: pyyaml>=6.0.3
Requires-Dist: rich>=14.1.0
Requires-Dist: tomlkit>=0.13.3
Requires-Dist: typer-slim>=0.19.2
Requires-Dist: types-pyyaml>=6.0.12.20250915
